<?xml version="1.0" encoding="UTF-8" standalone="no"?>
<root>
    <plant  name="002">
        <master_node  number="1">
            <type>74</type>
            <P>0.7069</P>
            <D>0.63</D>
            <mode>0</mode>
            <slots  number="1">
                <default>0</default>
            </slots>
        </master_node>
        <master_node  number="2">
            <type>75</type>
            <slots  number="1">
                <default>0</default>
            </slots>
            <slots  number="2">
                <default>0</default>
            </slots>
            <slots  number="3">
                <default>100</default>
            </slots>
            <slots  number="4">
                <default>20</default>
            </slots>
            <slots  number="5">
                <default>400</default>
            </slots>
        </master_node>
        <master_node  number="3">
            <type>64</type>
            <slots  number="1">
                <default>0</default>
            </slots>
            <slots  number="2">
                <default>0</default>
            </slots>
            <slots  number="3">
                <default>1</default>
            </slots>
        </master_node>
        <master_node  number="4">
            <type>67</type>
            <P>15</P>
            <I>0.1</I>
            <D>0.01</D>
            <extime>40</extime>
            <max_value>100</max_value>
            <min_value>0</min_value>
            <slots  number="1">
                <default>0</default>
            </slots>
            <slots  number="2">
                <default>0</default>
            </slots>
            <slots  number="3">
                <default>1</default>
            </slots>
            <slots  number="4">
                <default>0</default>
            </slots>
        </master_node>
        <master_node  number="5">
            <type>56</type>
            <slots  number="1">
                <default>0</default>
            </slots>
            <list  number="0">
                <default  number="0">0</default>
            </list>
            <list  number="1">
                <default  number="0">0</default>
            </list>
        </master_node>
    </plant>
</root>