{"datasArray":"[{\"t3144876242\":\"t5313378050\"},{\"t3018724808\":\"t7632690907\"}]","plants":"[{\"name\":\"001\",\"selected\":true,\"id\":\"p82474004375995\"},{\"name\":\"002\",\"selected\":false,\"id\":\"p44196850969456\"}]","gridpanelConfigs":"[{\"typegrid\":{\"icon\":\"resources/img/SVG/logic.svg\",\"title\":\"logic\",\"x\":273,\"y\":263,\"trsIds\":\"[\\\"t5489734876\\\",\\\"t8958164525\\\",\\\"t6592036930\\\",\\\"t5313378050\\\"]\"},\"store\":{\"data\":[{\"name\":\"Out\",\"value\":\"0\",\"delay\":\"0\",\"time\":\"0\",\"time1\":\"0\",\"time2\":\"0\",\"time3\":\"0\",\"time4\":\"0\",\"time5\":\"0\",\"time6\":\"0\",\"time7\":\"0\",\"time8\":\"0\",\"time9\":\"0\"},{\"name\":\"In\",\"value\":\"0\",\"delay\":\"0\",\"time\":\"0\",\"time1\":\"0\",\"time2\":\"0\",\"time3\":\"0\",\"time4\":\"0\",\"time5\":\"0\",\"time6\":\"0\",\"time7\":\"0\",\"time8\":\"0\",\"time9\":\"0\"},{\"name\":\"In\",\"value\":\"0\",\"delay\":\"0\",\"time\":\"0\",\"time1\":\"0\",\"time2\":\"0\",\"time3\":\"0\",\"time4\":\"0\",\"time5\":\"0\",\"time6\":\"0\",\"time7\":\"0\",\"time8\":\"0\",\"time9\":\"0\"},{\"name\":\"In\",\"value\":\"0\",\"delay\":\"0\",\"time\":\"0\",\"time1\":\"0\",\"time2\":\"0\",\"time3\":\"0\",\"time4\":\"0\",\"time5\":\"0\",\"time6\":\"0\",\"time7\":\"0\",\"time8\":\"0\",\"time9\":\"0\"}],\"fields\":[\"name\",\"value\",\"delay\",\"time\",\"time1\",\"time2\",\"time3\",\"time4\",\"time5\",\"time6\",\"time7\",\"time8\",\"time9\"]},\"datas\":{\"isAddSlot\":true,\"plantId\":\"p82474004375995\",\"type\":\"56\",\"rows\":7}},{\"typegrid\":{\"icon\":\"resources/img/SVG/logic.svg\",\"title\":\"logic\",\"x\":784,\"y\":235,\"trsIds\":\"[\\\"t9210499320\\\",\\\"t3018724808\\\",\\\"t8725609055\\\",\\\"t3144876242\\\"]\"},\"store\":{\"data\":[{\"name\":\"Out\",\"value\":\"0\",\"delay\":\"0\",\"time\":\"0\",\"time1\":\"0\",\"time2\":\"0\",\"time3\":\"0\",\"time4\":\"0\",\"time5\":\"0\",\"time6\":\"0\",\"time7\":\"0\",\"time8\":\"0\",\"time9\":\"0\"},{\"name\":\"In\",\"value\":\"0\",\"delay\":\"0\",\"time\":\"0\",\"time1\":\"0\",\"time2\":\"0\",\"time3\":\"0\",\"time4\":\"0\",\"time5\":\"0\",\"time6\":\"0\",\"time7\":\"0\",\"time8\":\"0\",\"time9\":\"0\"},{\"name\":\"In\",\"value\":\"0\",\"delay\":\"0\",\"time\":\"0\",\"time1\":\"0\",\"time2\":\"0\",\"time3\":\"0\",\"time4\":\"0\",\"time5\":\"0\",\"time6\":\"0\",\"time7\":\"0\",\"time8\":\"0\",\"time9\":\"0\"},{\"name\":\"In\",\"value\":\"0\",\"delay\":\"0\",\"time\":\"0\",\"time1\":\"0\",\"time2\":\"0\",\"time3\":\"0\",\"time4\":\"0\",\"time5\":\"0\",\"time6\":\"0\",\"time7\":\"0\",\"time8\":\"0\",\"time9\":\"0\"}],\"fields\":[\"name\",\"value\",\"delay\",\"time\",\"time1\",\"time2\",\"time3\",\"time4\",\"time5\",\"time6\",\"time7\",\"time8\",\"time9\"]},\"datas\":{\"isAddSlot\":true,\"plantId\":\"p82474004375995\",\"type\":\"56\",\"rows\":10}},{\"typegrid\":{\"icon\":\"resources/img/SVG/pid.svg\",\"title\":\"pid\",\"x\":446,\"y\":51,\"trsIds\":\"[\\\"t9730129996\\\",\\\"t5761639988\\\",\\\"t3714869082\\\",\\\"t8567250091\\\",\\\"t7632690907\\\"]\"},\"store\":{\"data\":[{\"name\":\"Out\",\"value\":\"0\"},{\"name\":\"PV\",\"value\":\"0\"},{\"name\":\"SP\",\"value\":\"0\"},{\"name\":\"Enable\",\"value\":\"Enable\",\"select\":[{\"name\":\"Enable\",\"value\":\"1\"},{\"name\":\"Disable\",\"value\":\"0\"}]},{\"name\":\"Direction\",\"value\":\"Derect\",\"select\":[{\"name\":\"Derect\",\"value\":\"0\"},{\"name\":\"Reverse\",\"value\":\"1\"}]}],\"fields\":[\"name\",\"value\"]},\"datas\":{\"isAddSlot\":false,\"plantId\":\"p82474004375995\",\"type\":\"67\"}}]"}